edgecore_engine_pro/__init__.py
edgecore_engine_pro/core.py
edgecore_engine_pro-3.0.0.dist-info/METADATA
edgecore_engine_pro-3.0.0.dist-info/WHEEL
edgecore_engine_pro-3.0.0.dist-info/entry_points.txt
edgecore_engine_pro-3.0.0.dist-info/top_level.txt
edgecore_engine_pro-3.0.0.dist-info/RECORD
